idepy/__init__.py
idepy/core/__init__.py
idepy/core/api.py
idepy/core/boot_start.py
idepy/core/builder.py
idepy/core/config.py
idepy/core/file.py
idepy/core/hotkeys.py
idepy/core/main.py
idepy/core/pywebview_file.py
idepy/core/server.py
idepy/core/settings.py
idepy/core/soft_server.py
idepy/core/tray_menu.py
idepy/core/utils.py
idepy/management/__init__.py
idepy/management/commandExecutor.py
idepy/management/commands/__init__.py
idepy/management/commands/build.py
idepy/management/commands/create_base_window.py
idepy/management/commands/init.py
idepy/management/commands/preview.py
idepy/templates/base_project/icon.ico
idepy/templates/base_project/idepy.json
idepy/templates/base_project/main.py
idepy/templates/base_project/manage.py
idepy/templates/base_project/static/package.json
idepy/templates/base_project/static/tailwind.config.js
idepy/templates/base_project/static/src/assets/logo.webp
idepy/templates/base_project/static/src/lib/idepy.css
idepy/templates/base_project/static/src/lib/idepy.js
idepy/templates/base_project/static/src/lib/lodash.js
idepy/templates/base_project/static/src/lib/tailwindcss.base.css
idepy/templates/base_project/static/src/lib/tailwindcss.css
idepy/templates/base_project/static/src/lib/utils.js
idepy/templates/base_project/static/src/lib/vue.global.js
idepy/templates/base_project/static/src/lib/element-plus/element-plus.css
idepy/templates/base_project/static/src/lib/element-plus/element-plus.js
idepy/templates/base_project/static/src/lib/element-plus/element-zh-cn.js
idepy/templates/base_project/static/src/lib/icon/iconfont.css
idepy/templates/base_project/static/src/lib/icon/iconfont.ttf
idepy/templates/base_project/static/src/lib/icon/iconfont.woff
idepy/templates/base_project/static/src/lib/icon/iconfont.woff2
idepy/templates/base_project/static/src/lib/qrcode/qrcode.min.js
idepy/templates/base_project/static/src/templates/footer.html
idepy/templates/base_project/static/src/templates/header.html
idepy-1.13.8.dist-info/LICENSE
idepy-1.13.8.dist-info/METADATA
idepy-1.13.8.dist-info/WHEEL
idepy-1.13.8.dist-info/entry_points.txt
idepy-1.13.8.dist-info/top_level.txt
idepy-1.13.8.dist-info/RECORD
