Metadata-Version: 2.1
Name: idepy
Version: 1.13.8
Summary: 开源免费的Python桌面应用开发框架
Home-page: https://idepy.com
Author: maplesunrise
Author-email: maplesunrise@foxmail.com
License: MIT
Classifier: License :: OSI Approved :: MIT License
Classifier: Programming Language :: Python :: 3
Classifier: Programming Language :: Python :: 3.12
Classifier: Operating System :: Microsoft :: Windows :: Windows 10
Classifier: Operating System :: Microsoft :: Windows :: Windows 11
Requires-Python: >=3.12
License-File: LICENSE
Requires-Dist: pywebview
Requires-Dist: pydash
Requires-Dist: pyinstaller
Requires-Dist: nuitka
Requires-Dist: cryptography
Requires-Dist: winshell
Requires-Dist: psutil
Requires-Dist: pywin32
Requires-Dist: keyboard
Requires-Dist: pystray
Requires-Dist: plyer
Requires-Dist: requests
Requires-Dist: Jinja2
